unbounded_thread_pool/__init__.py
unbounded_thread_pool/pool.py
unbounded_thread_pool-0.2.0.dist-info/LICENSE
unbounded_thread_pool-0.2.0.dist-info/METADATA
unbounded_thread_pool-0.2.0.dist-info/WHEEL
unbounded_thread_pool-0.2.0.dist-info/top_level.txt
unbounded_thread_pool-0.2.0.dist-info/RECORD
