Metadata-Version: 2.1
Name: unbounded-thread-pool
Version: 0.2.0
Summary: ThreadPool with unlimited workers count.
Home-page: https://github.com/romasku/unbounded-thread-pool
Author: romasku
Author-email: romasku135@gmail.com
License: MIT
Platform: UNKNOWN
Classifier: Intended Audience :: Developers
Classifier: Operating System :: OS Independent
Classifier: License :: OSI Approved :: MIT License
Classifier: Programming Language :: Python
Classifier: Programming Language :: Python :: 3
Classifier: Programming Language :: Python :: 3.6
Classifier: Programming Language :: Python :: 3.7
Classifier: Programming Language :: Python :: 3.8
Requires-Python: >=3.6
